zpp_ManagedFile/ManagedFile.py
zpp_ManagedFile/__init__.py
zpp_ManagedFile-1.0.2.dist-info/LICENSE
zpp_ManagedFile-1.0.2.dist-info/METADATA
zpp_ManagedFile-1.0.2.dist-info/WHEEL
zpp_ManagedFile-1.0.2.dist-info/top_level.txt
zpp_ManagedFile-1.0.2.dist-info/RECORD
