Metadata-Version: 2.1
Name: zpp_ManagedFile
Version: 1.0.2
Summary: Système de fichier managé pour le contrôle des actions sur un fichier
Home-page: https://github.com/ZephyrOff/zpp_ManagedFile
Author: 
License: MIT License
Project-URL: Documentation, https://github.com/ZephyrOff/zpp_ManagedFile
Platform: ALL
License-File: LICENSE
